ccsds/packets/europa_clipper/__init__.py
ccsds/packets/europa_clipper/common/__init__.py
ccsds/packets/europa_clipper/common/ccsds_header_footer.py
ccsds/packets/europa_clipper/common/hs_header.py
ccsds/packets/europa_clipper/common/metadata_pkt.py
ccsds/packets/europa_clipper/e_themis/__init__.py
ccsds/packets/europa_clipper/e_themis/apid_1474.py
ccsds/packets/europa_clipper/e_themis/metadata.py
ccsds/packets/europa_clipper/ecm/__init__.py
ccsds/packets/europa_clipper/ecm/fgx.py
ccsds/packets/europa_clipper/ecm/hs.py
ccsds/packets/europa_clipper/ecm/metadata.py
ccsds/packets/europa_clipper/ecm/reg_read.py
ccsds/packets/europa_clipper/eisnac/__init__.py
ccsds/packets/europa_clipper/eisnac/metadata.py
ccsds/packets/europa_clipper/eiswac/__init__.py
ccsds/packets/europa_clipper/eiswac/metadata.py
ccsds/packets/europa_clipper/maspex/__init__.py
ccsds/packets/europa_clipper/maspex/metadata.py
ccsds/packets/europa_clipper/mise/__init__.py
ccsds/packets/europa_clipper/mise/ancillary_fields.py
ccsds/packets/europa_clipper/mise/dark_histogram.py
ccsds/packets/europa_clipper/mise/decompression_converter.py
ccsds/packets/europa_clipper/mise/diag_count.py
ccsds/packets/europa_clipper/mise/diag_flag.py
ccsds/packets/europa_clipper/mise/diag_vector.py
ccsds/packets/europa_clipper/mise/frame_compressed.py
ccsds/packets/europa_clipper/mise/frame_support.py
ccsds/packets/europa_clipper/mise/frame_uncompressed_ancillary.py
ccsds/packets/europa_clipper/mise/frame_uncompressed_last.py
ccsds/packets/europa_clipper/mise/frame_uncompressed_preparser.py
ccsds/packets/europa_clipper/mise/frame_uncompressed_standard.py
ccsds/packets/europa_clipper/mise/metadata.py
ccsds/packets/europa_clipper/pimsl/__init__.py
ccsds/packets/europa_clipper/pimsl/metadata.py
ccsds/packets/europa_clipper/pimsu/__init__.py
ccsds/packets/europa_clipper/pimsu/metadata.py
ccsds/packets/europa_clipper/radmon/__init__.py
ccsds/packets/europa_clipper/radmon/metadata.py
ccsds/packets/europa_clipper/reason/__init__.py
pydownlinkparser-0.3.1.dist-info/LICENSE.md
pydownlinkparser-0.3.1.dist-info/METADATA
pydownlinkparser-0.3.1.dist-info/WHEEL
pydownlinkparser-0.3.1.dist-info/entry_points.txt
pydownlinkparser-0.3.1.dist-info/namespace_packages.txt
pydownlinkparser-0.3.1.dist-info/top_level.txt
pydownlinkparser-0.3.1.dist-info/zip-safe
pydownlinkparser-0.3.1.dist-info/RECORD
